CHANGELOG.txt
LICENSE.txt
MANIFEST.in
README.txt
setup.py
pythonnds/__init__.py
pythonnds/binarySearchTree.py
pythonnds/circularList.py
pythonnds/dequeue.py
pythonnds/doublylinkedlist.py
pythonnds/heap.py
pythonnds/linkedlist.py
pythonnds/queue.py
pythonnds/stack.py
pythonnds/trie.py
pythonnds.egg-info/PKG-INFO
pythonnds.egg-info/SOURCES.txt
pythonnds.egg-info/dependency_links.txt
pythonnds.egg-info/requires.txt
pythonnds.egg-info/top_level.txt