Metadata-Version: 2.1
Name: pythonnds
Version: 0.0.1
Summary: A package to help you while learning datastructures.
Home-page: http://py-ds-docs.vercel.app/
Author: Manish Tiwari
Author-email: manishsit13@gmail.com
License: MIT
Keywords: data structures
Platform: UNKNOWN
Classifier: Development Status :: 5 - Production/Stable
Classifier: Intended Audience :: Education
Classifier: Operating System :: Microsoft :: Windows :: Windows 10
Classifier: License :: OSI Approved :: MIT License
Classifier: Programming Language :: Python :: 3
License-File: LICENSE.txt
